infini_transformer_pytorch/__init__.py
infini_transformer_pytorch/infini_transformer.py
infini_transformer_pytorch/wrapper.py
infini_transformer_pytorch-0.2.1.dist-info/METADATA
infini_transformer_pytorch-0.2.1.dist-info/WHEEL
infini_transformer_pytorch-0.2.1.dist-info/licenses/LICENSE
infini_transformer_pytorch-0.2.1.dist-info/RECORD
