Metadata-Version: 2.4
Name: infini-transformer-pytorch
Version: 0.2.1
Summary: Infini-Transformer in Pytorch
Project-URL: Homepage, https://pypi.org/project/infini-transformer-pytorch/
Project-URL: Repository, https://github.com/lucidrains/infini-transformer-pytorch
Author-email: Phil Wang <lucidrains@gmail.com>
License: MIT License
License-File: LICENSE
Keywords: artificial intelligence,attention mechanism,deep learning,long context,memory,transformers
Classifier: Development Status :: 4 - Beta
Classifier: Intended Audience :: Developers
Classifier: License :: OSI Approved :: MIT License
Classifier: Programming Language :: Python :: 3.8
Classifier: Topic :: Scientific/Engineering :: Artificial Intelligence
Requires-Python: >=3.8
Requires-Dist: einops>=0.8.0
Requires-Dist: rotary-embedding-torch>=0.6.0
Requires-Dist: torch>=2.0
Requires-Dist: tqdm
Provides-Extra: examples
Requires-Dist: numpy; extra == 'examples'
Requires-Dist: tqdm; extra == 'examples'
